Metadata-Version: 2.1
Name: django-oasis4-auth
Version: 1.1.0
Summary: Oasis 4 Authorization System for django
Author-email: Mario Cerón <mario.ceron@cqinversiones.co>
License: CQ INVERSIONES S.A.S.
Keywords: django,OASIS4
Classifier: License :: Other/Proprietary License
Classifier: Programming Language :: Python :: 3.9
Classifier: Development Status :: 5 - Production/Stable
Classifier: Framework :: Django
Classifier: Framework :: Django :: 4.1
Classifier: Environment :: Web Environment
Classifier: Operating System :: OS Independent
Classifier: Topic :: Internet :: WWW/HTTP
Requires-Python: >=3.9
License-File: LICENSE
Requires-Dist: Django (>=4.1)
Requires-Dist: djangorestframework
Requires-Dist: django-oasis4 (>=1.0.4)
Requires-Dist: zibanu-django (>=1.2.0)
